transcript_insightful/__init__.py
transcript_insightful/main.py
transcript_insightful/prompts.py
transcript_insightful-2025.12.21185930.dist-info/METADATA
transcript_insightful-2025.12.21185930.dist-info/WHEEL
transcript_insightful-2025.12.21185930.dist-info/top_level.txt
transcript_insightful-2025.12.21185930.dist-info/RECORD
