Metadata-Version: 2.4
Name: transcript-insightful
Version: 2025.12.21185930
Summary: transcript-insightful extracts and structures key insights from video transcripts, delivering concise themes and implications.
Author-email: transcript-insightful <hi@eugene.plus>
License: MIT
Project-URL: Homepage, https://github.com/chigwell/transcript-insightful
Requires-Python: >=3.9
Requires-Dist: langchain-llm7>=0.0.0
Requires-Dist: llmatch-messages>=0.0.0
Requires-Dist: langchain-core>=0.3.0
